hquant.py
hquant-0.1.0.dist-info/LICENSE
hquant-0.1.0.dist-info/WHEEL
hquant-0.1.0.dist-info/METADATA
hquant-0.1.0.dist-info/RECORD
