Metadata-Version: 2.1
Name: hquant
Version: 0.1.0
Summary: High quality quantization for Pillow images.
Keywords: image,dither,dithering,quantization,palette
Author-email: Marcos Del Sol Vives <marcos@orca.pet>
Requires-Python: >=3.8
Classifier: License :: Freely Distributable
Classifier: Operating System :: OS Independent
Classifier: Programming Language :: Python :: 3
Classifier: Programming Language :: Python :: 3.8
Classifier: Programming Language :: Python :: 3.9
Classifier: Programming Language :: Python :: 3.10
Classifier: Programming Language :: Python :: 3.11
Classifier: Programming Language :: Python :: 3.12
Classifier: Topic :: Multimedia
Classifier: Topic :: Multimedia :: Graphics
Classifier: Topic :: Multimedia :: Graphics :: Graphics Conversion
Classifier: Typing :: Typed
Requires-Dist: Pillow >=9.0.0
Project-URL: Homepage, https://github.com/socram8888/hquant
Project-URL: Issues, https://github.com/socram8888/hquant/issues
